{
  "2": {
    "total_mJ": 14982239772.516705,
    "total_ceq": 1402.6445402495526,
    "num_expired_thresh": 0,
    "num_depleted": 0,
    "num_transmited_bytes": 8096138688,
    "num_participants": 10,
    "num_failures": 0
  },
  "3": {
    "total_mJ": 8909085834.991043,
    "total_ceq": 830.9680596438193,
    "num_expired_thresh": 0,
    "num_depleted": 0,
    "num_transmited_bytes": 8096138688,
    "num_participants": 10,
    "num_failures": 0
  },
  "4": {
    "total_mJ": 14687609478.236069,
    "total_ceq": 1379.9518148248467,
    "num_expired_thresh": 0,
    "num_depleted": 0,
    "num_transmited_bytes": 8096138688,
    "num_participants": 10,
    "num_failures": 0
  },
  "5": {
    "total_mJ": 7244906511.117512,
    "total_ceq": 694.7808128027744,
    "num_expired_thresh": 0,
    "num_depleted": 0,
    "num_transmited_bytes": 8096138688,
    "num_participants": 10,
    "num_failures": 0
  },
  "6": {
    "total_mJ": 5855344921.316219,
    "total_ceq": 559.0710417551549,
    "num_expired_thresh": 0,
    "num_depleted": 0,
    "num_transmited_bytes": 8096138688,
    "num_participants": 10,
    "num_failures": 0
  },
  "7": {
    "total_mJ": 13603080513.609556,
    "total_ceq": 1264.2221378918205,
    "num_expired_thresh": 0,
    "num_depleted": 0,
    "num_transmited_bytes": 8096138688,
    "num_participants": 10,
    "num_failures": 0
  },
  "8": {
    "total_mJ": 6208211252.278688,
    "total_ceq": 591.7882241116134,
    "num_expired_thresh": 0,
    "num_depleted": 0,
    "num_transmited_bytes": 8096138688,
    "num_participants": 10,
    "num_failures": 0
  },
  "9": {
    "total_mJ": 5112447764.379901,
    "total_ceq": 501.2664196844056,
    "num_expired_thresh": 0,
    "num_depleted": 0,
    "num_transmited_bytes": 8096138688,
    "num_participants": 10,
    "num_failures": 0
  },
  "10": {
    "total_mJ": 11008469575.780993,
    "total_ceq": 1021.5330415565516,
    "num_expired_thresh": 0,
    "num_depleted": 0,
    "num_transmited_bytes": 8096138688,
    "num_participants": 10,
    "num_failures": 0
  },
  "11": {
    "total_mJ": 13940623047.625095,
    "total_ceq": 1299.970016658461,
    "num_expired_thresh": 0,
    "num_depleted": 0,
    "num_transmited_bytes": 8096138688,
    "num_participants": 10,
    "num_failures": 0
  },
  "12": {
    "total_mJ": 8983503072.752697,
    "total_ceq": 833.4207111137009,
    "num_expired_thresh": 0,
    "num_depleted": 0,
    "num_transmited_bytes": 8096138688,
    "num_participants": 10,
    "num_failures": 0
  },
  "13": {
    "total_mJ": 5116426639.625981,
    "total_ceq": 502.81076411912335,
    "num_expired_thresh": 0,
    "num_depleted": 0,
    "num_transmited_bytes": 8096138688,
    "num_participants": 10,
    "num_failures": 0
  },
  "14": {
    "total_mJ": 5684896275.513875,
    "total_ceq": 543.0163339641234,
    "num_expired_thresh": 0,
    "num_depleted": 0,
    "num_transmited_bytes": 8096138688,
    "num_participants": 10,
    "num_failures": 0
  },
  "15": {
    "total_mJ": 9106447415.19109,
    "total_ceq": 860.3625101810047,
    "num_expired_thresh": 0,
    "num_depleted": 0,
    "num_transmited_bytes": 8096138688,
    "num_participants": 10,
    "num_failures": 0
  },
  "16": {
    "total_mJ": 13627306028.392141,
    "total_ceq": 1291.5625762655839,
    "num_expired_thresh": 0,
    "num_depleted": 0,
    "num_transmited_bytes": 8096138688,
    "num_participants": 10,
    "num_failures": 0
  },
  "17": {
    "total_mJ": 11035587586.18313,
    "total_ceq": 1049.5681047186408,
    "num_expired_thresh": 0,
    "num_depleted": 0,
    "num_transmited_bytes": 8096138688,
    "num_participants": 10,
    "num_failures": 0
  },
  "18": {
    "total_mJ": 9287782920.77356,
    "total_ceq": 875.3755446940245,
    "num_expired_thresh": 0,
    "num_depleted": 0,
    "num_transmited_bytes": 8096138688,
    "num_participants": 10,
    "num_failures": 0
  },
  "19": {
    "total_mJ": 8440137163.772159,
    "total_ceq": 789.5764252094006,
    "num_expired_thresh": 0,
    "num_depleted": 0,
    "num_transmited_bytes": 8096138688,
    "num_participants": 10,
    "num_failures": 0
  },
  "20": {
    "total_mJ": 5648262220.907685,
    "total_ceq": 548.0422345447554,
    "num_expired_thresh": 0,
    "num_depleted": 0,
    "num_transmited_bytes": 8096138688,
    "num_participants": 10,
    "num_failures": 0
  },
  "21": {
    "total_mJ": 9294319964.908607,
    "total_ceq": 886.2657131882795,
    "num_expired_thresh": 0,
    "num_depleted": 0,
    "num_transmited_bytes": 8096138688,
    "num_participants": 10,
    "num_failures": 0
  },
  "22": {
    "total_mJ": 9276677141.443642,
    "total_ceq": 864.4454641092843,
    "num_expired_thresh": 0,
    "num_depleted": 0,
    "num_transmited_bytes": 8096138688,
    "num_participants": 10,
    "num_failures": 0
  },
  "23": {
    "total_mJ": 8887045977.743057,
    "total_ceq": 835.2558223328546,
    "num_expired_thresh": 0,
    "num_depleted": 0,
    "num_transmited_bytes": 8096138688,
    "num_participants": 10,
    "num_failures": 0
  },
  "24": {
    "total_mJ": 8445886036.659414,
    "total_ceq": 816.6646109473186,
    "num_expired_thresh": 0,
    "num_depleted": 0,
    "num_transmited_bytes": 8096138688,
    "num_participants": 10,
    "num_failures": 0
  },
  "25": {
    "total_mJ": 9037367214.35949,
    "total_ceq": 839.8434466670512,
    "num_expired_thresh": 0,
    "num_depleted": 0,
    "num_transmited_bytes": 8096138688,
    "num_participants": 10,
    "num_failures": 0
  },
  "26": {
    "total_mJ": 8401638885.862296,
    "total_ceq": 790.3295257224804,
    "num_expired_thresh": 0,
    "num_depleted": 0,
    "num_transmited_bytes": 8096138688,
    "num_participants": 10,
    "num_failures": 0
  },
  "27": {
    "total_mJ": 8445697149.449865,
    "total_ceq": 801.6646026343111,
    "num_expired_thresh": 0,
    "num_depleted": 0,
    "num_transmited_bytes": 8096138688,
    "num_participants": 10,
    "num_failures": 0
  },
  "28": {
    "total_mJ": 14794536847.611486,
    "total_ceq": 1381.4859218536537,
    "num_expired_thresh": 0,
    "num_depleted": 0,
    "num_transmited_bytes": 8096138688,
    "num_participants": 10,
    "num_failures": 0
  },
  "29": {
    "total_mJ": 9298995846.872114,
    "total_ceq": 874.5592444307432,
    "num_expired_thresh": 0,
    "num_depleted": 0,
    "num_transmited_bytes": 8096138688,
    "num_participants": 10,
    "num_failures": 0
  },
  "30": {
    "total_mJ": 14620609646.500454,
    "total_ceq": 1373.5679940705577,
    "num_expired_thresh": 0,
    "num_depleted": 0,
    "num_transmited_bytes": 8096138688,
    "num_participants": 10,
    "num_failures": 0
  },
  "31": {
    "total_mJ": 6351596471.768693,
    "total_ceq": 616.0456749907437,
    "num_expired_thresh": 0,
    "num_depleted": 0,
    "num_transmited_bytes": 8096138688,
    "num_participants": 10,
    "num_failures": 0
  },
  "32": {
    "total_mJ": 14731492045.976595,
    "total_ceq": 1381.7059024049406,
    "num_expired_thresh": 0,
    "num_depleted": 0,
    "num_transmited_bytes": 8096138688,
    "num_participants": 10,
    "num_failures": 0
  },
  "33": {
    "total_mJ": 8479826832.671607,
    "total_ceq": 793.8642984011998,
    "num_expired_thresh": 0,
    "num_depleted": 0,
    "num_transmited_bytes": 8096138688,
    "num_participants": 10,
    "num_failures": 0
  },
  "34": {
    "total_mJ": 14724082931.51628,
    "total_ceq": 1371.3031738742507,
    "num_expired_thresh": 0,
    "num_depleted": 0,
    "num_transmited_bytes": 8096138688,
    "num_participants": 10,
    "num_failures": 0
  },
  "35": {
    "total_mJ": 5180225792.353286,
    "total_ceq": 524.1073955256315,
    "num_expired_thresh": 0,
    "num_depleted": 0,
    "num_transmited_bytes": 8096138688,
    "num_participants": 10,
    "num_failures": 0
  },
  "36": {
    "total_mJ": 8412080120.56904,
    "total_ceq": 792.0395552202506,
    "num_expired_thresh": 0,
    "num_depleted": 0,
    "num_transmited_bytes": 8096138688,
    "num_participants": 10,
    "num_failures": 0
  },
  "37": {
    "total_mJ": 11096512032.057873,
    "total_ceq": 1047.8197770833651,
    "num_expired_thresh": 0,
    "num_depleted": 0,
    "num_transmited_bytes": 8096138688,
    "num_participants": 10,
    "num_failures": 0
  },
  "38": {
    "total_mJ": 8968118819.585361,
    "total_ceq": 857.4611063161749,
    "num_expired_thresh": 0,
    "num_depleted": 0,
    "num_transmited_bytes": 8096138688,
    "num_participants": 10,
    "num_failures": 0
  },
  "39": {
    "total_mJ": 15171571721.160393,
    "total_ceq": 1411.5781560318803,
    "num_expired_thresh": 0,
    "num_depleted": 0,
    "num_transmited_bytes": 8096138688,
    "num_participants": 10,
    "num_failures": 0
  },
  "40": {
    "total_mJ": 9063117244.436962,
    "total_ceq": 846.2880717778403,
    "num_expired_thresh": 0,
    "num_depleted": 0,
    "num_transmited_bytes": 8096138688,
    "num_participants": 10,
    "num_failures": 0
  },
  "41": {
    "total_mJ": 11072109355.887138,
    "total_ceq": 1036.414824289824,
    "num_expired_thresh": 0,
    "num_depleted": 0,
    "num_transmited_bytes": 8096138688,
    "num_participants": 10,
    "num_failures": 0
  },
  "42": {
    "total_mJ": 8999838881.687729,
    "total_ceq": 862.2719353190765,
    "num_expired_thresh": 0,
    "num_depleted": 0,
    "num_transmited_bytes": 8096138688,
    "num_participants": 10,
    "num_failures": 0
  },
  "43": {
    "total_mJ": 9005682820.745047,
    "total_ceq": 847.5892740220991,
    "num_expired_thresh": 0,
    "num_depleted": 0,
    "num_transmited_bytes": 8096138688,
    "num_participants": 10,
    "num_failures": 0
  },
  "44": {
    "total_mJ": 14857288257.842749,
    "total_ceq": 1403.5384104940174,
    "num_expired_thresh": 0,
    "num_depleted": 0,
    "num_transmited_bytes": 8096138688,
    "num_participants": 10,
    "num_failures": 0
  },
  "45": {
    "total_mJ": 13598224812.541534,
    "total_ceq": 1271.6724104545228,
    "num_expired_thresh": 0,
    "num_depleted": 0,
    "num_transmited_bytes": 8096138688,
    "num_participants": 10,
    "num_failures": 0
  },
  "46": {
    "total_mJ": 5244289088.877583,
    "total_ceq": 509.23960233214126,
    "num_expired_thresh": 0,
    "num_depleted": 0,
    "num_transmited_bytes": 8096138688,
    "num_participants": 10,
    "num_failures": 0
  },
  "47": {
    "total_mJ": 9133019599.624706,
    "total_ceq": 854.5133385831109,
    "num_expired_thresh": 0,
    "num_depleted": 0,
    "num_transmited_bytes": 8096138688,
    "num_participants": 10,
    "num_failures": 0
  },
  "48": {
    "total_mJ": 13978921271.431417,
    "total_ceq": 1314.593848638386,
    "num_expired_thresh": 0,
    "num_depleted": 0,
    "num_transmited_bytes": 8096138688,
    "num_participants": 10,
    "num_failures": 0
  },
  "49": {
    "total_mJ": 14701396152.122011,
    "total_ceq": 1383.8908468721095,
    "num_expired_thresh": 0,
    "num_depleted": 0,
    "num_transmited_bytes": 8096138688,
    "num_participants": 10,
    "num_failures": 0
  },
  "50": {
    "total_mJ": 9181237284.55068,
    "total_ceq": 892.4418569349493,
    "num_expired_thresh": 0,
    "num_depleted": 0,
    "num_transmited_bytes": 8096138688,
    "num_participants": 10,
    "num_failures": 0
  },
  "51": {
    "total_mJ": 15085759697.192694,
    "total_ceq": 1407.0974458073779,
    "num_expired_thresh": 0,
    "num_depleted": 0,
    "num_transmited_bytes": 8096138688,
    "num_participants": 10,
    "num_failures": 0
  },
  "52": {
    "total_mJ": 9011028934.567812,
    "total_ceq": 844.2899944376617,
    "num_expired_thresh": 0,
    "num_depleted": 0,
    "num_transmited_bytes": 8096138688,
    "num_participants": 10,
    "num_failures": 0
  },
  "53": {
    "total_mJ": 6896327736.143644,
    "total_ceq": 646.1482339486847,
    "num_expired_thresh": 0,
    "num_depleted": 0,
    "num_transmited_bytes": 8096138688,
    "num_participants": 10,
    "num_failures": 0
  },
  "54": {
    "total_mJ": 13796196486.75756,
    "total_ceq": 1295.6385897360672,
    "num_expired_thresh": 0,
    "num_depleted": 0,
    "num_transmited_bytes": 8096138688,
    "num_participants": 10,
    "num_failures": 0
  },
  "55": {
    "total_mJ": 7452367025.028974,
    "total_ceq": 701.3132810229653,
    "num_expired_thresh": 0,
    "num_depleted": 0,
    "num_transmited_bytes": 8096138688,
    "num_participants": 10,
    "num_failures": 0
  },
  "56": {
    "total_mJ": 5958787573.832545,
    "total_ceq": 596.3410748169065,
    "num_expired_thresh": 0,
    "num_depleted": 0,
    "num_transmited_bytes": 8096138688,
    "num_participants": 10,
    "num_failures": 0
  },
  "57": {
    "total_mJ": 13939602455.529484,
    "total_ceq": 1302.6690672856919,
    "num_expired_thresh": 0,
    "num_depleted": 0,
    "num_transmited_bytes": 8096138688,
    "num_participants": 10,
    "num_failures": 0
  },
  "58": {
    "total_mJ": 9135156351.22887,
    "total_ceq": 860.0381216607758,
    "num_expired_thresh": 0,
    "num_depleted": 0,
    "num_transmited_bytes": 8096138688,
    "num_participants": 10,
    "num_failures": 0
  },
  "59": {
    "total_mJ": 7664839149.009634,
    "total_ceq": 730.3629083611262,
    "num_expired_thresh": 0,
    "num_depleted": 0,
    "num_transmited_bytes": 8096138688,
    "num_participants": 10,
    "num_failures": 0
  },
  "60": {
    "total_mJ": 7775410962.306921,
    "total_ceq": 737.0156761536829,
    "num_expired_thresh": 0,
    "num_depleted": 0,
    "num_transmited_bytes": 8096138688,
    "num_participants": 10,
    "num_failures": 0
  },
  "61": {
    "total_mJ": 14684177030.5503,
    "total_ceq": 1380.209100546605,
    "num_expired_thresh": 0,
    "num_depleted": 0,
    "num_transmited_bytes": 8096138688,
    "num_participants": 10,
    "num_failures": 0
  },
  "62": {
    "total_mJ": 8383992228.396025,
    "total_ceq": 796.5826080599427,
    "num_expired_thresh": 0,
    "num_depleted": 0,
    "num_transmited_bytes": 8096138688,
    "num_participants": 10,
    "num_failures": 0
  },
  "63": {
    "total_mJ": 8941054485.44931,
    "total_ceq": 834.8785124144409,
    "num_expired_thresh": 0,
    "num_depleted": 0,
    "num_transmited_bytes": 8096138688,
    "num_participants": 10,
    "num_failures": 0
  },
  "64": {
    "total_mJ": 8351872957.7700815,
    "total_ceq": 795.1740754343298,
    "num_expired_thresh": 0,
    "num_depleted": 0,
    "num_transmited_bytes": 8096138688,
    "num_participants": 10,
    "num_failures": 0
  },
  "65": {
    "total_mJ": 13851358406.13295,
    "total_ceq": 1305.1591165768893,
    "num_expired_thresh": 0,
    "num_depleted": 0,
    "num_transmited_bytes": 8096138688,
    "num_participants": 10,
    "num_failures": 0
  },
  "66": {
    "total_mJ": 14026612897.970203,
    "total_ceq": 1307.0175532149265,
    "num_expired_thresh": 0,
    "num_depleted": 0,
    "num_transmited_bytes": 8096138688,
    "num_participants": 10,
    "num_failures": 0
  },
  "67": {
    "total_mJ": 11045861476.630095,
    "total_ceq": 1039.1218637774114,
    "num_expired_thresh": 0,
    "num_depleted": 0,
    "num_transmited_bytes": 8096138688,
    "num_participants": 10,
    "num_failures": 0
  },
  "68": {
    "total_mJ": 14857833311.268547,
    "total_ceq": 1388.5476200035519,
    "num_expired_thresh": 0,
    "num_depleted": 0,
    "num_transmited_bytes": 8096138688,
    "num_participants": 10,
    "num_failures": 0
  },
  "69": {
    "total_mJ": 14918828720.70909,
    "total_ceq": 1421.345443060625,
    "num_expired_thresh": 0,
    "num_depleted": 0,
    "num_transmited_bytes": 8096138688,
    "num_participants": 10,
    "num_failures": 0
  },
  "70": {
    "total_mJ": 8381761444.815564,
    "total_ceq": 792.6249943917702,
    "num_expired_thresh": 0,
    "num_depleted": 0,
    "num_transmited_bytes": 8096138688,
    "num_participants": 10,
    "num_failures": 0
  },
  "71": {
    "total_mJ": 9039532733.188261,
    "total_ceq": 838.8385589614783,
    "num_expired_thresh": 0,
    "num_depleted": 0,
    "num_transmited_bytes": 8096138688,
    "num_participants": 10,
    "num_failures": 0
  },
  "72": {
    "total_mJ": 4466428947.396768,
    "total_ceq": 434.9775715558537,
    "num_expired_thresh": 0,
    "num_depleted": 0,
    "num_transmited_bytes": 8096138688,
    "num_participants": 10,
    "num_failures": 0
  },
  "73": {
    "total_mJ": 8290957676.899195,
    "total_ceq": 784.8423970497117,
    "num_expired_thresh": 0,
    "num_depleted": 0,
    "num_transmited_bytes": 8096138688,
    "num_participants": 10,
    "num_failures": 0
  },
  "74": {
    "total_mJ": 14964988023.948776,
    "total_ceq": 1404.7946088547192,
    "num_expired_thresh": 0,
    "num_depleted": 0,
    "num_transmited_bytes": 8096138688,
    "num_participants": 10,
    "num_failures": 0
  },
  "75": {
    "total_mJ": 7706846327.108362,
    "total_ceq": 735.2805134745435,
    "num_expired_thresh": 0,
    "num_depleted": 0,
    "num_transmited_bytes": 8096138688,
    "num_participants": 10,
    "num_failures": 0
  },
  "76": {
    "total_mJ": 14993751438.027405,
    "total_ceq": 1414.2844368706324,
    "num_expired_thresh": 0,
    "num_depleted": 0,
    "num_transmited_bytes": 8096138688,
    "num_participants": 10,
    "num_failures": 0
  },
  "77": {
    "total_mJ": 7245074150.186048,
    "total_ceq": 688.081539835071,
    "num_expired_thresh": 0,
    "num_depleted": 0,
    "num_transmited_bytes": 8096138688,
    "num_participants": 10,
    "num_failures": 0
  },
  "78": {
    "total_mJ": 9176125728.670437,
    "total_ceq": 871.0280798065967,
    "num_expired_thresh": 0,
    "num_depleted": 0,
    "num_transmited_bytes": 8096138688,
    "num_participants": 10,
    "num_failures": 0
  },
  "79": {
    "total_mJ": 9087455575.24437,
    "total_ceq": 861.1744479556286,
    "num_expired_thresh": 0,
    "num_depleted": 0,
    "num_transmited_bytes": 8096138688,
    "num_participants": 10,
    "num_failures": 0
  },
  "80": {
    "total_mJ": 7773413643.985016,
    "total_ceq": 743.5851451942233,
    "num_expired_thresh": 0,
    "num_depleted": 0,
    "num_transmited_bytes": 8096138688,
    "num_participants": 10,
    "num_failures": 0
  },
  "81": {
    "total_mJ": 8403464977.476664,
    "total_ceq": 801.7851051050993,
    "num_expired_thresh": 0,
    "num_depleted": 0,
    "num_transmited_bytes": 8096138688,
    "num_participants": 10,
    "num_failures": 0
  },
  "82": {
    "total_mJ": 15006053554.549044,
    "total_ceq": 1400.3384612645111,
    "num_expired_thresh": 0,
    "num_depleted": 0,
    "num_transmited_bytes": 8096138688,
    "num_participants": 10,
    "num_failures": 0
  },
  "83": {
    "total_mJ": 8931080564.81754,
    "total_ceq": 855.9882071668995,
    "num_expired_thresh": 0,
    "num_depleted": 0,
    "num_transmited_bytes": 8096138688,
    "num_participants": 10,
    "num_failures": 0
  },
  "84": {
    "total_mJ": 13572495283.662066,
    "total_ceq": 1265.830009048919,
    "num_expired_thresh": 0,
    "num_depleted": 0,
    "num_transmited_bytes": 8096138688,
    "num_participants": 10,
    "num_failures": 0
  },
  "85": {
    "total_mJ": 6509801322.384445,
    "total_ceq": 618.9262610503547,
    "num_expired_thresh": 0,
    "num_depleted": 0,
    "num_transmited_bytes": 8096138688,
    "num_participants": 10,
    "num_failures": 0
  },
  "86": {
    "total_mJ": 9301403009.905268,
    "total_ceq": 866.0667230572142,
    "num_expired_thresh": 0,
    "num_depleted": 0,
    "num_transmited_bytes": 8096138688,
    "num_participants": 10,
    "num_failures": 0
  },
  "87": {
    "total_mJ": 13879948201.720469,
    "total_ceq": 1311.1995425820724,
    "num_expired_thresh": 0,
    "num_depleted": 0,
    "num_transmited_bytes": 8096138688,
    "num_participants": 10,
    "num_failures": 0
  },
  "88": {
    "total_mJ": 5152708317.0769825,
    "total_ceq": 508.5126737570534,
    "num_expired_thresh": 0,
    "num_depleted": 0,
    "num_transmited_bytes": 8096138688,
    "num_participants": 10,
    "num_failures": 0
  },
  "89": {
    "total_mJ": 13982311112.824589,
    "total_ceq": 1306.8760045777713,
    "num_expired_thresh": 0,
    "num_depleted": 0,
    "num_transmited_bytes": 8096138688,
    "num_participants": 10,
    "num_failures": 0
  },
  "90": {
    "total_mJ": 6398675086.770928,
    "total_ceq": 594.7605208822982,
    "num_expired_thresh": 0,
    "num_depleted": 0,
    "num_transmited_bytes": 8096138688,
    "num_participants": 10,
    "num_failures": 0
  },
  "91": {
    "total_mJ": 13982264786.149174,
    "total_ceq": 1309.2901229379568,
    "num_expired_thresh": 0,
    "num_depleted": 0,
    "num_transmited_bytes": 8096138688,
    "num_participants": 10,
    "num_failures": 0
  },
  "92": {
    "total_mJ": 14711195512.92261,
    "total_ceq": 1375.4770973028697,
    "num_expired_thresh": 0,
    "num_depleted": 0,
    "num_transmited_bytes": 8096138688,
    "num_participants": 10,
    "num_failures": 0
  },
  "93": {
    "total_mJ": 7217915282.703636,
    "total_ceq": 688.3228625368017,
    "num_expired_thresh": 0,
    "num_depleted": 0,
    "num_transmited_bytes": 8096138688,
    "num_participants": 10,
    "num_failures": 0
  },
  "94": {
    "total_mJ": 5810047357.000796,
    "total_ceq": 560.7221346969997,
    "num_expired_thresh": 0,
    "num_depleted": 0,
    "num_transmited_bytes": 8096138688,
    "num_participants": 10,
    "num_failures": 0
  },
  "95": {
    "total_mJ": 13869750254.23632,
    "total_ceq": 1292.3697091987874,
    "num_expired_thresh": 0,
    "num_depleted": 0,
    "num_transmited_bytes": 8096138688,
    "num_participants": 10,
    "num_failures": 0
  },
  "96": {
    "total_mJ": 8924824103.559143,
    "total_ceq": 845.704180706596,
    "num_expired_thresh": 0,
    "num_depleted": 0,
    "num_transmited_bytes": 8096138688,
    "num_participants": 10,
    "num_failures": 0
  },
  "97": {
    "total_mJ": 8945286791.177954,
    "total_ceq": 845.5564453556028,
    "num_expired_thresh": 0,
    "num_depleted": 0,
    "num_transmited_bytes": 8096138688,
    "num_participants": 10,
    "num_failures": 0
  },
  "98": {
    "total_mJ": 6104794673.554875,
    "total_ceq": 589.1950772485545,
    "num_expired_thresh": 0,
    "num_depleted": 0,
    "num_transmited_bytes": 8096138688,
    "num_participants": 10,
    "num_failures": 0
  },
  "99": {
    "total_mJ": 6230527708.108844,
    "total_ceq": 599.6568209426441,
    "num_expired_thresh": 0,
    "num_depleted": 0,
    "num_transmited_bytes": 8096138688,
    "num_participants": 10,
    "num_failures": 0
  },
  "100": {
    "total_mJ": 7770778126.538323,
    "total_ceq": 745.6857367610978,
    "num_expired_thresh": 0,
    "num_depleted": 0,
    "num_transmited_bytes": 8096138688,
    "num_participants": 10,
    "num_failures": 0
  },
  "101": {
    "total_mJ": 13862211087.160807,
    "total_ceq": 1305.6685191393503,
    "num_expired_thresh": 0,
    "num_depleted": 0,
    "num_transmited_bytes": 8096138688,
    "num_participants": 10,
    "num_failures": 0
  },
  "102": {
    "total_mJ": 9310335796.228224,
    "total_ceq": 884.7114711748732,
    "num_expired_thresh": 0,
    "num_depleted": 0,
    "num_transmited_bytes": 8096138688,
    "num_participants": 10,
    "num_failures": 0
  },
  "103": {
    "total_mJ": 14644256072.79401,
    "total_ceq": 1393.2871783856053,
    "num_expired_thresh": 0,
    "num_depleted": 0,
    "num_transmited_bytes": 8096138688,
    "num_participants": 10,
    "num_failures": 0
  },
  "104": {
    "total_mJ": 14721590509.143032,
    "total_ceq": 1403.163736036408,
    "num_expired_thresh": 0,
    "num_depleted": 0,
    "num_transmited_bytes": 8096138688,
    "num_participants": 10,
    "num_failures": 0
  },
  "105": {
    "total_mJ": 14746726749.946745,
    "total_ceq": 1374.477896495919,
    "num_expired_thresh": 0,
    "num_depleted": 0,
    "num_transmited_bytes": 8096138688,
    "num_participants": 10,
    "num_failures": 0
  },
  "106": {
    "total_mJ": 7251899462.046568,
    "total_ceq": 687.9110895541722,
    "num_expired_thresh": 0,
    "num_depleted": 0,
    "num_transmited_bytes": 8096138688,
    "num_participants": 10,
    "num_failures": 0
  },
  "107": {
    "total_mJ": 6259827104.8389015,
    "total_ceq": 586.8384196321875,
    "num_expired_thresh": 0,
    "num_depleted": 0,
    "num_transmited_bytes": 8096138688,
    "num_participants": 10,
    "num_failures": 0
  },
  "108": {
    "total_mJ": 14974774835.462378,
    "total_ceq": 1409.677190716144,
    "num_expired_thresh": 0,
    "num_depleted": 0,
    "num_transmited_bytes": 8096138688,
    "num_participants": 10,
    "num_failures": 0
  },
  "109": {
    "total_mJ": 14966799119.066427,
    "total_ceq": 1411.8597264940593,
    "num_expired_thresh": 0,
    "num_depleted": 0,
    "num_transmited_bytes": 8096138688,
    "num_participants": 10,
    "num_failures": 0
  },
  "110": {
    "total_mJ": 8888226607.272596,
    "total_ceq": 844.9086592267325,
    "num_expired_thresh": 0,
    "num_depleted": 0,
    "num_transmited_bytes": 8096138688,
    "num_participants": 10,
    "num_failures": 0
  },
  "111": {
    "total_mJ": 7334401989.547704,
    "total_ceq": 696.5529226948225,
    "num_expired_thresh": 0,
    "num_depleted": 0,
    "num_transmited_bytes": 8096138688,
    "num_participants": 10,
    "num_failures": 0
  },
  "112": {
    "total_mJ": 8280007230.343858,
    "total_ceq": 787.059265818445,
    "num_expired_thresh": 0,
    "num_depleted": 0,
    "num_transmited_bytes": 8096138688,
    "num_participants": 10,
    "num_failures": 0
  },
  "113": {
    "total_mJ": 7221358097.968397,
    "total_ceq": 690.6903284973495,
    "num_expired_thresh": 0,
    "num_depleted": 0,
    "num_transmited_bytes": 8096138688,
    "num_participants": 10,
    "num_failures": 0
  },
  "114": {
    "total_mJ": 7702811424.842623,
    "total_ceq": 728.5888591787904,
    "num_expired_thresh": 0,
    "num_depleted": 0,
    "num_transmited_bytes": 8096138688,
    "num_participants": 10,
    "num_failures": 0
  },
  "115": {
    "total_mJ": 8452962008.189456,
    "total_ceq": 786.259046494703,
    "num_expired_thresh": 0,
    "num_depleted": 0,
    "num_transmited_bytes": 8096138688,
    "num_participants": 10,
    "num_failures": 0
  },
  "116": {
    "total_mJ": 14762379822.781927,
    "total_ceq": 1386.1961968955416,
    "num_expired_thresh": 0,
    "num_depleted": 0,
    "num_transmited_bytes": 8096138688,
    "num_participants": 10,
    "num_failures": 0
  },
  "117": {
    "total_mJ": 14704242559.722998,
    "total_ceq": 1385.8786944359686,
    "num_expired_thresh": 0,
    "num_depleted": 0,
    "num_transmited_bytes": 8096138688,
    "num_participants": 10,
    "num_failures": 0
  },
  "118": {
    "total_mJ": 14605231512.148169,
    "total_ceq": 1366.609878815454,
    "num_expired_thresh": 0,
    "num_depleted": 0,
    "num_transmited_bytes": 8096138688,
    "num_participants": 10,
    "num_failures": 0
  },
  "119": {
    "total_mJ": 14778674509.160404,
    "total_ceq": 1383.1466216882627,
    "num_expired_thresh": 0,
    "num_depleted": 0,
    "num_transmited_bytes": 8096138688,
    "num_participants": 10,
    "num_failures": 0
  },
  "120": {
    "total_mJ": 6225190644.509746,
    "total_ceq": 575.9607369203736,
    "num_expired_thresh": 0,
    "num_depleted": 0,
    "num_transmited_bytes": 8096138688,
    "num_participants": 10,
    "num_failures": 0
  },
  "121": {
    "total_mJ": 14688380794.411587,
    "total_ceq": 1393.0421795837706,
    "num_expired_thresh": 0,
    "num_depleted": 0,
    "num_transmited_bytes": 8096138688,
    "num_participants": 10,
    "num_failures": 0
  },
  "122": {
    "total_mJ": 6919383718.349198,
    "total_ceq": 679.893573305532,
    "num_expired_thresh": 0,
    "num_depleted": 0,
    "num_transmited_bytes": 8096138688,
    "num_participants": 10,
    "num_failures": 0
  },
  "123": {
    "total_mJ": 9220554536.502436,
    "total_ceq": 868.5847978088939,
    "num_expired_thresh": 0,
    "num_depleted": 0,
    "num_transmited_bytes": 8096138688,
    "num_participants": 10,
    "num_failures": 0
  },
  "124": {
    "total_mJ": 13994488642.30922,
    "total_ceq": 1319.4598279432134,
    "num_expired_thresh": 0,
    "num_depleted": 0,
    "num_transmited_bytes": 8096138688,
    "num_participants": 10,
    "num_failures": 0
  },
  "125": {
    "total_mJ": 14005558285.405916,
    "total_ceq": 1318.3496689643384,
    "num_expired_thresh": 0,
    "num_depleted": 0,
    "num_transmited_bytes": 8096138688,
    "num_participants": 10,
    "num_failures": 0
  },
  "126": {
    "total_mJ": 14762727292.281242,
    "total_ceq": 1391.5312615778637,
    "num_expired_thresh": 0,
    "num_depleted": 0,
    "num_transmited_bytes": 8096138688,
    "num_participants": 10,
    "num_failures": 0
  },
  "127": {
    "total_mJ": 10928131670.511997,
    "total_ceq": 1034.7319006335997,
    "num_expired_thresh": 0,
    "num_depleted": 0,
    "num_transmited_bytes": 8096138688,
    "num_participants": 10,
    "num_failures": 0
  },
  "128": {
    "total_mJ": 11029056951.096611,
    "total_ceq": 1043.93555627602,
    "num_expired_thresh": 0,
    "num_depleted": 0,
    "num_transmited_bytes": 8096138688,
    "num_participants": 10,
    "num_failures": 0
  },
  "129": {
    "total_mJ": 9051366748.931383,
    "total_ceq": 853.7359447794933,
    "num_expired_thresh": 0,
    "num_depleted": 0,
    "num_transmited_bytes": 8096138688,
    "num_participants": 10,
    "num_failures": 0
  },
  "130": {
    "total_mJ": 8501758429.82005,
    "total_ceq": 789.7337712484349,
    "num_expired_thresh": 0,
    "num_depleted": 0,
    "num_transmited_bytes": 8096138688,
    "num_participants": 10,
    "num_failures": 0
  },
  "131": {
    "total_mJ": 9116031291.713526,
    "total_ceq": 848.6166868149936,
    "num_expired_thresh": 0,
    "num_depleted": 0,
    "num_transmited_bytes": 8096138688,
    "num_participants": 10,
    "num_failures": 0
  },
  "132": {
    "total_mJ": 6177445865.689243,
    "total_ceq": 588.3966796880493,
    "num_expired_thresh": 0,
    "num_depleted": 0,
    "num_transmited_bytes": 8096138688,
    "num_participants": 10,
    "num_failures": 0
  },
  "133": {
    "total_mJ": 13620883023.346071,
    "total_ceq": 1280.1853546295367,
    "num_expired_thresh": 0,
    "num_depleted": 0,
    "num_transmited_bytes": 8096138688,
    "num_participants": 10,
    "num_failures": 0
  },
  "134": {
    "total_mJ": 8981224978.883007,
    "total_ceq": 859.7631335587588,
    "num_expired_thresh": 0,
    "num_depleted": 0,
    "num_transmited_bytes": 8096138688,
    "num_participants": 10,
    "num_failures": 0
  },
  "135": {
    "total_mJ": 8972544056.75971,
    "total_ceq": 854.0652088095638,
    "num_expired_thresh": 0,
    "num_depleted": 0,
    "num_transmited_bytes": 8096138688,
    "num_participants": 10,
    "num_failures": 0
  },
  "136": {
    "total_mJ": 8905599780.69817,
    "total_ceq": 838.3505754821254,
    "num_expired_thresh": 0,
    "num_depleted": 0,
    "num_transmited_bytes": 8096138688,
    "num_participants": 10,
    "num_failures": 0
  },
  "137": {
    "total_mJ": 9319276986.731335,
    "total_ceq": 872.2948054279483,
    "num_expired_thresh": 0,
    "num_depleted": 0,
    "num_transmited_bytes": 8096138688,
    "num_participants": 10,
    "num_failures": 0
  },
  "138": {
    "total_mJ": 9017294162.749002,
    "total_ceq": 857.3439179093186,
    "num_expired_thresh": 0,
    "num_depleted": 0,
    "num_transmited_bytes": 8096138688,
    "num_participants": 10,
    "num_failures": 0
  },
  "139": {
    "total_mJ": 15020419944.430876,
    "total_ceq": 1401.4163718265888,
    "num_expired_thresh": 0,
    "num_depleted": 0,
    "num_transmited_bytes": 8096138688,
    "num_participants": 10,
    "num_failures": 0
  },
  "140": {
    "total_mJ": 6305310769.501962,
    "total_ceq": 614.611422312474,
    "num_expired_thresh": 0,
    "num_depleted": 0,
    "num_transmited_bytes": 8096138688,
    "num_participants": 10,
    "num_failures": 0
  },
  "141": {
    "total_mJ": 9236746367.956013,
    "total_ceq": 896.9711252807725,
    "num_expired_thresh": 0,
    "num_depleted": 0,
    "num_transmited_bytes": 8096138688,
    "num_participants": 10,
    "num_failures": 0
  },
  "142": {
    "total_mJ": 6185766184.395952,
    "total_ceq": 594.7748186214042,
    "num_expired_thresh": 0,
    "num_depleted": 0,
    "num_transmited_bytes": 8096138688,
    "num_participants": 10,
    "num_failures": 0
  },
  "143": {
    "total_mJ": 7724965088.217269,
    "total_ceq": 720.4301991106553,
    "num_expired_thresh": 0,
    "num_depleted": 0,
    "num_transmited_bytes": 8096138688,
    "num_participants": 10,
    "num_failures": 0
  },
  "144": {
    "total_mJ": 8970931109.409971,
    "total_ceq": 849.5803143284963,
    "num_expired_thresh": 0,
    "num_depleted": 0,
    "num_transmited_bytes": 8096138688,
    "num_participants": 10,
    "num_failures": 0
  },
  "145": {
    "total_mJ": 9261117142.497505,
    "total_ceq": 887.4034844418718,
    "num_expired_thresh": 0,
    "num_depleted": 0,
    "num_transmited_bytes": 8096138688,
    "num_participants": 10,
    "num_failures": 0
  },
  "146": {
    "total_mJ": 14762469479.403214,
    "total_ceq": 1386.9172274124696,
    "num_expired_thresh": 0,
    "num_depleted": 0,
    "num_transmited_bytes": 8096138688,
    "num_participants": 10,
    "num_failures": 0
  },
  "147": {
    "total_mJ": 6157212298.0698805,
    "total_ceq": 581.7753805105294,
    "num_expired_thresh": 0,
    "num_depleted": 0,
    "num_transmited_bytes": 8096138688,
    "num_participants": 10,
    "num_failures": 0
  },
  "148": {
    "total_mJ": 13833316728.916893,
    "total_ceq": 1296.725828855637,
    "num_expired_thresh": 0,
    "num_depleted": 0,
    "num_transmited_bytes": 8096138688,
    "num_participants": 10,
    "num_failures": 0
  },
  "149": {
    "total_mJ": 11027335712.948824,
    "total_ceq": 1029.6834164418724,
    "num_expired_thresh": 0,
    "num_depleted": 0,
    "num_transmited_bytes": 8096138688,
    "num_participants": 10,
    "num_failures": 0
  },
  "150": {
    "total_mJ": 11011322524.314821,
    "total_ceq": 1053.8182983563413,
    "num_expired_thresh": 0,
    "num_depleted": 0,
    "num_transmited_bytes": 8096138688,
    "num_participants": 10,
    "num_failures": 0
  },
  "151": {
    "total_mJ": 9134581123.829544,
    "total_ceq": 842.4922719568866,
    "num_expired_thresh": 0,
    "num_depleted": 0,
    "num_transmited_bytes": 8096138688,
    "num_participants": 10,
    "num_failures": 0
  }
}